xldiff/__init__.py
xldiff/__main__.py
xldiff/app.py
xldiff/diff.py
xldiff-0.1.0.dist-info/entry_points.txt
xldiff-0.1.0.dist-info/LICENSE
xldiff-0.1.0.dist-info/WHEEL
xldiff-0.1.0.dist-info/METADATA
xldiff-0.1.0.dist-info/RECORD
