Metadata-Version: 2.1
Name: xldiff
Version: 0.1.0
Summary: A dead-simple command line diffing of datasets stored in Excel
Home-page: https://github.com/glesica/xldiff
License: UNKNOWN
Author: George Lesica
Author-email: george@lesica.com
Requires-Python: >=3.6
Classifier: License :: OSI Approved :: MIT License
Requires-Dist: openpyxl
